LICENSE.txt
MANIFEST.in
README.txt
changelog.txt
setup.py
cofan/__init__.py
cofan/__main__.py
cofan/cofan.py
cofan.egg-info/PKG-INFO
cofan.egg-info/SOURCES.txt
cofan.egg-info/dependency_links.txt
cofan.egg-info/requires.txt
cofan.egg-info/top_level.txt
cofan/main_tree/localhost_tree/provider.py
cofan/main_tree/others_tree/provider.py
cofan/providers/__init__.py
cofan/providers/base_provider.py
cofan/providers/filer.py
cofan/providers/iconer.py
cofan/providers/ip_patterner.py
cofan/providers/password_checker.py
cofan/providers/pattern_lister.py
cofan/providers/patterner.py
cofan/providers/statuser.py
cofan/providers/ziper.py
cofan/providers/asset/filer_main.html
cofan/providers/asset/themes/humanity.zip
cofan/providers/asset/themes/plane.zip
cofan/providers/asset/themes/zafiro.zip
cofan/utils/misc.py
cofan/utils/tfman.py