Metadata-Version: 2.1
Name: cofan
Version: 1.0.0
Summary: http server to serve files and other things.
Home-page: https://github.com/alghafli/cofan
Author: Mohammad Alghafli
Author-email: thebsom@gmail.com
License: UNKNOWN
Keywords: http file server
Platform: UNKNOWN
Classifier: Development Status :: 4 - Beta
Classifier: Intended Audience :: Developers
Classifier: License :: OSI Approved :: GNU General Public License v3 (GPLv3)
Classifier: Programming Language :: Python :: 3.5
License-File: LICENSE.txt
